{
  "book_id": 3253,
  "book_uuid": "9f288042-86ae-42bb-b119-739e5d14ef06",
  "title": "A Catskill Eagle",
  "pubdate": "2010-07-07 17:57:20.232326+00:00",
  "isbn": "",
  "author_name": "Robert B. Parker",
  "publisher_name": "Random House Publishing Group",
  "series_name": "",
  "series_index": 1.0,
  "tags": [
    "Fiction",
    "Mystery & Detective",
    "Hard-Boiled",
    "Thrillers",
    "Private Investigators",
    "Crime"
  ],
  "description": "<p>Susan's letter came from California: Hand was in jail, and she was on the run. Twenty-four hours later, Hawk is free, because Spenser has sprung him loose\u2014for a brutal cross-country journey back to the East Coast. Now the two men are on a violent ride to find the woman Spenser loves, the man who took her, and the shocking reason so many people had to die. . . .\u00a0Praise for A Catskill Eagle\u201cEntertaining.\u201d\u2014The San Diego Union-Tribune\u201cHis best mystery novel.\u201d\u2014Time</p>"
}