{
  "book_id": 3545,
  "book_uuid": "4fc8a9bd-9fca-430e-bdd4-a86ac17ca03f",
  "title": "The Moviegoer",
  "pubdate": "2010-06-15 04:00:00+00:00",
  "isbn": "",
  "author_name": "Walker Percy",
  "publisher_name": "Open Road Integrated Media LLC",
  "series_name": "",
  "series_index": 1.0,
  "tags": [],
  "description": "<div><p>Percy's National Book Award\u00ad\u2013winning classic: A young man, torn between the forces of tradition and change, searches for meaning in post-war America</p><p>On the cusp of his thirtieth birthday, Binx Bolling is a lost soul. A stockbroker and member of an established New Orleans family, Binx's one escape is the movie theater that transports him from the falseness of his life. With Mardi Gras in full swing, Binx, along with his cousin Kate, sets out to find his true purpose amid the excesses of the carnival that surrounds him.</p><p>Buoyant yet powerful, The Moviegoer is a poignant indictment of modern values, and an unforgettable story of a week that will change two lives forever.</p></div>"
}