{
  "book_id": 3624,
  "book_uuid": "0839b379-4623-434d-927c-80816fd4df1a",
  "title": "The stars my destination",
  "pubdate": "1996-07-02 19:00:06.264000+00:00",
  "isbn": "",
  "author_name": "Alfred Bester; Alex Eisenstein; Phyllis Eisenstein",
  "publisher_name": "Vintage Books",
  "series_name": "",
  "series_index": 1.0,
  "tags": [
    "Fiction",
    "General",
    "Science Fiction",
    "Sci-Fi",
    "Fiction - Science Fiction",
    "Science Fiction - General",
    "Revenge",
    "Castaways",
    "Bester",
    "Alfred - Prose & Criticism",
    "Sciencefiction",
    "Astrology & Fortune-telling",
    "Star signs & horoscopes"
  ],
  "description": "SUMMARY: Marooned in outer space after an attack on his ship, Nomad, Gulliver Foyle lives to obsessively pursue the crew of a rescue vessel that had intended to leave him to die. Reprint. 10,000 first printing."
}