{
  "book_id": 805,
  "book_uuid": "340b15be-9201-4ee6-b578-0dbab53a4b3c",
  "title": "Westworld",
  "pubdate": "1974-03-16 07:00:00+00:00",
  "isbn": "",
  "author_name": "Michael Crichton",
  "publisher_name": "Bantam Books",
  "series_name": "Delos",
  "series_index": 1.0,
  "tags": [
    88,
    373
  ],
  "description": "<div><p class=\"description\"><b>Epub v4</b></p><p class=\"description\"><b>Live out your fantasies for $1,000 a day at Westworld\u2014the ultimate resort!</b></p>\n<p class=\"description\">Murder, violence, wild sexual abandon, any human desire is fulfilled by totally computerized, humanoid robots programed for your pleasure alone . . . Until a small computer casualty spreads like wildfire and one man stands alone against the berserk machines bent on total slaughter!</p>\n<p class=\"description\"><b>An adventure in total terror!</b></p></div>"
}